tselect/__init__.py
tselect/abstract_extractor.py
tselect/catch22.py
tselect/channel_selectors/__init__.py
tselect/channel_selectors/random_channel_selector.py
tselect/channel_selectors/tselect.py
tselect/channel_selectors/wrappers.py
tselect/config.py
tselect/minirocket.py
tselect/rank_correlation/__init__.py
tselect/rank_correlation/rank_correlation.py
tselect/rank_correlation/setup.py
tselect/rank_correlation/spearman.pyx
tselect/tsfresh.py
tselect/univariate_ensemble.py
tselect/utils/__init__.py
tselect/utils/constants.py
tselect/utils/scaler.py
tsfuse/__init__.py
tsfuse/computation/__init__.py
tsfuse/computation/apply.py
tsfuse/computation/graph.py
tsfuse/computation/nodes.py
tsfuse/computation/util.py
tsfuse/construction/__init__.py
tsfuse/construction/mlj20.py
tsfuse/data/__init__.py
tsfuse/data/df.pyx
tsfuse/data/synthetic.py
tsfuse/data/tags.py
tsfuse/data/units.py
tsfuse/errors.py
tsfuse/transformers/__init__.py
tsfuse/transformers/boolean.py
tsfuse/transformers/calculators/__init__.py
tsfuse/transformers/calculators/cstatistics.pyx
tsfuse/transformers/calculators/queries.pyx
tsfuse/transformers/calculators/setup.py
tsfuse/transformers/calculators/setup_cstatistics.py
tsfuse/transformers/calculators/setup_queries.py
tsfuse/transformers/conversion.py
tsfuse/transformers/frequency.py
tsfuse/transformers/geometry.py
tsfuse/transformers/mathematics.py
tsfuse/transformers/peaks.py
tsfuse/transformers/queries.py
tsfuse/transformers/sampling.py
tsfuse/transformers/statistics.py
tsfuse/transformers/uniqueness.py
tsfuse/transformers/util.py
tsfuse/utils/__init__.py
tselect-1.0.0.dist-info/LICENSE
tselect-1.0.0.dist-info/METADATA
tselect-1.0.0.dist-info/WHEEL
tselect-1.0.0.dist-info/RECORD
