Metadata-Version: 2.1
Name: tselect
Version: 1.0.0
Summary: Package for selecting the relevant and non-redundant channels for multivariate time series classification.
Author: Loren Nuyts
Author-email: loren.nuyts@kuleuven.be
Requires-Python: >=3.10
Classifier: Programming Language :: Python :: 3
Classifier: Programming Language :: Python :: 3.10
Classifier: Programming Language :: Python :: 3.11
Requires-Dist: cython (>=3.1.4,<4.0.0)
Requires-Dist: matplotlib (>=3.10.6,<4.0.0)
Requires-Dist: numpy (>=2.2.6)
Requires-Dist: pandas (>=2.3.2,<3.0.0)
Requires-Dist: pycatch22 (>=0.4.5,<0.5.0)
Requires-Dist: scikit-learn (>=1.6.1)
Requires-Dist: scipy (>=1.15.3)
Requires-Dist: setuptools (>=80.9.0,<81.0.0)
Requires-Dist: sktime (>=0.38.5,<0.39.0)
